tessToPy/__init__.py
tessToPy/absdict.py
tessToPy/geometry.py
tessToPy/original_tessellation_processing.py
tessToPy/tessIO.py
tessToPy/tessellation.py
tessToPy-0.0.12.dist-info/LICENSE.md
tessToPy-0.0.12.dist-info/METADATA
tessToPy-0.0.12.dist-info/WHEEL
tessToPy-0.0.12.dist-info/top_level.txt
tessToPy-0.0.12.dist-info/RECORD
