Metadata-Version: 2.1
Name: tessToPy
Version: 0.0.12
Summary: My package description
Home-page: https://github.com/DanielThorM/tessToPy
Author: Daniel Morton
Author-email: dan.mort.alt@gmail.com
License: MIT
Keywords: tessellation,voronoi,laguerre,periodic,regularized
Platform: UNKNOWN
Classifier: Programming Language :: Python :: 3.7
Requires-Python: >=3.7
Requires-Dist: numpy (>=1.20)
Requires-Dist: matplotlib (>=3.4)
Requires-Dist: scipy (>=1.6)
